README.md
setup.cfg
setup.py
docdump/__init__.py
docdump/excel.py
docdump/main.py
docdump/metadata.py
docdump/pdf.py
docdump/powerpoint.py
docdump/text.py
docdump/word.py
docdump.egg-info/PKG-INFO
docdump.egg-info/SOURCES.txt
docdump.egg-info/dependency_links.txt
docdump.egg-info/requires.txt
docdump.egg-info/top_level.txt