Metadata-Version: 2.1
Name: docdump
Version: 1.0.4
Summary: A package to extract text from common document types.
Home-page: https://github.com/Gholtes/docdump
Author: Grant Holtes
Author-email: gwholes@gmail.com
License: MIT
Keywords: nlp,text processing,document,pdf,Microsoft office,text
Platform: UNKNOWN
